SRT/__init__.py
SRT/constants.py
SRT/errors.py
SRT/netfunnel.py
SRT/passenger.py
SRT/reservation.py
SRT/response_data.py
SRT/seat_type.py
SRT/srt.py
SRT/train.py
srtrain-2.6.5.dist-info/METADATA
srtrain-2.6.5.dist-info/WHEEL
srtrain-2.6.5.dist-info/licenses/LICENSE
srtrain-2.6.5.dist-info/RECORD
