Metadata-Version: 2.4
Name: SRTrain
Version: 2.6.5
Summary: SRT(Super Rapid Train) wrapper for python
Project-URL: Homepage, https://github.com/ryanking13/SRT
Project-URL: Bug Tracker, https://github.com/ryanking13/SRT/issues
Project-URL: Changelog, https://github.com/ryanking13/SRT/blob/master/CHANGELOG.md
Author-email: Gyeongjae Choi <def6488@gmail.com>
License: MIT License
License-File: LICENSE
Requires-Python: >=3.10
Requires-Dist: requests
Provides-Extra: test
Requires-Dist: black==23.12.1; extra == 'test'
Requires-Dist: pre-commit; extra == 'test'
Requires-Dist: pytest; extra == 'test'
Requires-Dist: pytest-httpserver; extra == 'test'
